tensorflew/__init__.py
tensorflew/core.py
tensorflew-0.1.6.dist-info/METADATA
tensorflew-0.1.6.dist-info/WHEEL
tensorflew-0.1.6.dist-info/top_level.txt
tensorflew-0.1.6.dist-info/RECORD
